bugpilot/__init__.py
bugpilot/__main__.py
bugpilot/advanced_tools.py
bugpilot/file_mention_parser.py
bugpilot/filesystem.py
bugpilot/logic_engine.py
bugpilot/main.py
bugpilot/workflow_manager.py
bugpilot/agent/__init__.py
bugpilot/agent/controller.py
bugpilot/agent/executor.py
bugpilot/agent/intent_detector.py
bugpilot/cli/__init__.py
bugpilot/cli/autocomplete.py
bugpilot/cli/handlers.py
bugpilot/cli/helpers.py
bugpilot/core/__init__.py
bugpilot/core/models.py
bugpilot/core/status_bar.py
bugpilot/core/terminal_ui.py
bugpilot/core/updater.py
bugpilot/core/utils.py
bugpilot/core/config/__init__.py
bugpilot/core/config/defaults.yaml
bugpilot/core/config/editor.py
bugpilot/core/config/schema.py
bugpilot/core/config/settings.py
bugpilot/core/config/settings.yaml
bugpilot/core/llm/__init__.py
bugpilot/core/llm/anthropic.py
bugpilot/core/llm/base.py
bugpilot/core/llm/factory.py
bugpilot/core/llm/gemini.py
bugpilot/core/llm/groq.py
bugpilot/core/llm/ollama.py
bugpilot/core/llm/registry.py
bugpilot/core/prompts/__init__.py
bugpilot/core/prompts/common.py
bugpilot/core/prompts/hacker.py
bugpilot/core/prompts/normal.py
bugpilot/core/prompts/tools.py
bugpilot/core/state/__init__.py
bugpilot/core/state/context.py
bugpilot/core/state/memory.py
bugpilot/core/state/session.py
bugpilot/core/utils/__init__.py
bugpilot/core/utils/os_detection.py
bugpilot/modes/__init__.py
bugpilot/modes/forge.py
bugpilot/modes/hacker.py
bugpilot/tools/__init__.py
bugpilot/tools/knowledge.py
bugpilot/tools/manager.py
bugpilot/tools/mcp.py
bugpilot/tools/security_knowledge.py
bugpilot_cli-1.3.5.dist-info/LICENSE
bugpilot_cli-1.3.5.dist-info/METADATA
bugpilot_cli-1.3.5.dist-info/WHEEL
bugpilot_cli-1.3.5.dist-info/entry_points.txt
bugpilot_cli-1.3.5.dist-info/top_level.txt
bugpilot_cli-1.3.5.dist-info/RECORD
