Metadata-Version: 2.1
Name: bugpilot-cli
Version: 1.3.5
Summary: AI-Powered Autonomous Penetration Testing CLI
Home-page: https://github.com/letchupkt/bugpilot-cli
Author: LAKSHMIKANTHAN K
Author-email: letchupkt@example.com
Classifier: Development Status :: 4 - Beta
Classifier: Intended Audience :: Developers
Classifier: Intended Audience :: Information Technology
Classifier: Topic :: Security
Classifier: License :: OSI Approved :: MIT License
Classifier: Programming Language :: Python :: 3
Classifier: Programming Language :: Python :: 3.8
Classifier: Programming Language :: Python :: 3.9
Classifier: Programming Language :: Python :: 3.10
Classifier: Programming Language :: Python :: 3.11
Requires-Python: >=3.8
License-File: LICENSE
Requires-Dist: rich>=13.0.0
Requires-Dist: prompt-toolkit>=3.0.36
Requires-Dist: google-generativeai>=0.3.0
Requires-Dist: anthropic>=0.7.0
Requires-Dist: groq>=0.4.0
Requires-Dist: PyYAML>=6.0
Requires-Dist: requests>=2.31.0
